{
  "FilePath": "d:\\Documents\\Programi\\Blazor\\blazortoastify-git\\BlazorToastify\\src\\BlazorToastify\\BlazorToastify.csproj",
  "Configuration": {
    "ConfigurationName": "Default",
    "LanguageVersion": "3.0",
    "Extensions": []
  },
  "ProjectWorkspaceState": {
    "TagHelpers": [],
    "CSharpLanguageVersion": 703
  },
  "RootNamespace": "BlazorToastify",
  "Documents": [
    {
      "FilePath": "d:\\Documents\\Programi\\Blazor\\blazortoastify-git\\BlazorToastify\\src\\BlazorToastify\\ToastContainer.razor",
      "TargetPath": "ToastContainer.razor",
      "FileKind": "component"
    },
    {
      "FilePath": "d:\\Documents\\Programi\\Blazor\\blazortoastify-git\\BlazorToastify\\src\\BlazorToastify\\_Imports.razor",
      "TargetPath": "_Imports.razor",
      "FileKind": "componentImport"
    }
  ],
  "SerializationFormat": "0.2"
}